hats_import/__init__.py
hats_import/_version.py
hats_import/pipeline.py
hats_import/pipeline_resume_plan.py
hats_import/py.typed
hats_import/runtime_arguments.py
hats_import/association/__init__.py
hats_import/association/arguments.py
hats_import/catalog/__init__.py
hats_import/catalog/arguments.py
hats_import/catalog/map_reduce.py
hats_import/catalog/resume_plan.py
hats_import/catalog/run_import.py
hats_import/catalog/file_readers/__init__.py
hats_import/catalog/file_readers/csv.py
hats_import/catalog/file_readers/ecsv.py
hats_import/catalog/file_readers/fits.py
hats_import/catalog/file_readers/input_reader.py
hats_import/catalog/file_readers/parquet.py
hats_import/collection/__init__.py
hats_import/collection/arguments.py
hats_import/collection/run_import.py
hats_import/hipscat_conversion/__init__.py
hats_import/hipscat_conversion/arguments.py
hats_import/hipscat_conversion/run_conversion.py
hats_import/index/__init__.py
hats_import/index/arguments.py
hats_import/index/map_reduce.py
hats_import/index/run_index.py
hats_import/margin_cache/__init__.py
hats_import/margin_cache/margin_cache.py
hats_import/margin_cache/margin_cache_arguments.py
hats_import/margin_cache/margin_cache_map_reduce.py
hats_import/margin_cache/margin_cache_resume_plan.py
hats_import/verification/__init__.py
hats_import/verification/arguments.py
hats_import/verification/run_verification.py
hats_import-0.7.3.dist-info/licenses/LICENSE
hats_import-0.7.3.dist-info/METADATA
hats_import-0.7.3.dist-info/WHEEL
hats_import-0.7.3.dist-info/top_level.txt
hats_import-0.7.3.dist-info/RECORD
