Metadata-Version: 2.4
Name: hats-import
Version: 0.7.3
Summary: Utility for ingesting large survey data into HATS structure
Author-email: LINCC Frameworks <lincc-frameworks-team@lists.lsst.org>
License-Expression: BSD-3-Clause
Classifier: Development Status :: 4 - Beta
Classifier: Intended Audience :: Developers
Classifier: Intended Audience :: Science/Research
Classifier: Operating System :: OS Independent
Classifier: Programming Language :: Python
Requires-Python: >=3.10
License-File: LICENSE
Requires-Dist: cloudpickle>=3.0.0
Requires-Dist: dask[complete]<2025.4.0,>=2025.3.0
Requires-Dist: deprecated
Requires-Dist: hats<0.8,>=0.7.3
Requires-Dist: nested-pandas<0.7.0,>=0.6.3
Requires-Dist: numpy<3,>=2.2.0
Requires-Dist: pandas>=2.0
Requires-Dist: tqdm>=4.59.0
Requires-Dist: universal-pathlib
Provides-Extra: dev
Requires-Dist: black; extra == "dev"
Requires-Dist: jupyter; extra == "dev"
Requires-Dist: mypy; extra == "dev"
Requires-Dist: pre-commit; extra == "dev"
Requires-Dist: pylint; extra == "dev"
Requires-Dist: pytest; extra == "dev"
Requires-Dist: pytest-cov; extra == "dev"
Requires-Dist: pytest-mock; extra == "dev"
Requires-Dist: pytest-timeout; extra == "dev"
Provides-Extra: full
Requires-Dist: fsspec[full]; extra == "full"
Requires-Dist: ipykernel; extra == "full"
Requires-Dist: ipywidgets; extra == "full"
Requires-Dist: healpy; extra == "full"
Dynamic: license-file
